groundmeas/__init__.py
groundmeas/analytics.py
groundmeas/cli.py
groundmeas/core/__init__.py
groundmeas/core/db.py
groundmeas/core/models.py
groundmeas/db.py
groundmeas/export.py
groundmeas/models.py
groundmeas/plots.py
groundmeas/services/__init__.py
groundmeas/services/analytics.py
groundmeas/services/export.py
groundmeas/services/vision_import.py
groundmeas/ui/__init__.py
groundmeas/ui/cli.py
groundmeas/ui/dashboard.py
groundmeas/vision_import.py
groundmeas/visualization/__init__.py
groundmeas/visualization/map_vis.py
groundmeas/visualization/plots.py
groundmeas/visualization/vis_plotly.py
groundmeas-1.4.0.dist-info/METADATA
groundmeas-1.4.0.dist-info/WHEEL
groundmeas-1.4.0.dist-info/entry_points.txt
groundmeas-1.4.0.dist-info/licenses/LICENSE
groundmeas-1.4.0.dist-info/RECORD
