Metadata-Version: 2.4
Name: groundmeas
Version: 1.4.0
Summary: 
License-File: LICENSE
Author: Christian Ehlert
Author-email: christian.ehlert@mailbox.org
Requires-Python: >=3.14
Classifier: Programming Language :: Python :: 3
Classifier: Programming Language :: Python :: 3.14
Requires-Dist: folium (>=0.19.4,<1.0.0)
Requires-Dist: matplotlib (>=3.10.8,<4.0.0)
Requires-Dist: numpy (>=2.2.5,<3.0.0)
Requires-Dist: opencv-python-headless (>=4.11.0.86,<5.0.0)
Requires-Dist: pandas (>=2.2.3,<3.0.0)
Requires-Dist: plotly (>=6.5.0,<7.0.0)
Requires-Dist: prompt_toolkit (>=3.0.48,<4.0.0)
Requires-Dist: pytesseract (>=0.3.13,<0.4.0)
Requires-Dist: requests (>=2.32.3,<3.0.0)
Requires-Dist: scipy (>=1.17.0,<2.0.0)
Requires-Dist: sqlite-utils (>=3.38,<4.0)
Requires-Dist: sqlmodel (>=0.0.31,<0.0.32)
Requires-Dist: streamlit (>=1.52.2,<2.0.0)
Requires-Dist: streamlit-folium (>=0.25.3,<0.26.0)
Requires-Dist: typer (>=0.15.3,<0.16.0)
